authrocket
