Metadata-Version: 1.1
Name: authrocket
Version: 0.1.1
Summary: Unofficial AuthRocket API client
Home-page: https://github.com/nathforge/authrocket
Author: Nathan Reynolds
Author-email: email@nreynolds.co.uk
License: UNKNOWN
Platform: UNKNOWN
Classifier: Development Status :: 4 - Beta
Classifier: Intended Audience :: Developers
Classifier: Topic :: Software Development
Classifier: License :: OSI Approved :: MIT License
